.gitignore
.travis.yml
CHANGELOG.rst
CONTRIBUTING.rst
COPYING
INSTALL
MANIFEST.in
PKG-INFO
README.rst
codecov.yml
readthedocs.yml
requirements.txt
setup.cfg
setup.py
tox.ini
.github/ISSUE_TEMPLATE.md
.github/PULL_REQUEST_TEMPLATE.md
doc/.gitignore
doc/Makefile
doc/conf.py
doc/index.rst
doc/make.bat
doc/pyescpos.ico
doc/requirements.txt
doc/_build/html/_sources/index.txt
doc/_build/html/_sources/api/config.txt
doc/_build/html/_sources/api/constants.txt
doc/_build/html/_sources/api/escpos.txt
doc/_build/html/_sources/api/exceptions.txt
doc/_build/html/_sources/api/image.txt
doc/_build/html/_sources/api/printer.txt
doc/_build/html/_sources/apidoc/escpos.txt
doc/_build/html/_sources/apidoc/modules.txt
doc/_build/html/_sources/dev/changelog.txt
doc/_build/html/_sources/dev/contributing.txt
doc/_build/html/_sources/user/barcode.txt
doc/_build/html/_sources/user/dependencies.txt
doc/_build/html/_sources/user/installation.txt
doc/_build/html/_sources/user/methods.txt
doc/_build/html/_sources/user/printers.txt
doc/_build/html/_sources/user/raspi.txt
doc/_build/html/_sources/user/todo.txt
doc/_build/html/_sources/user/usage.txt
doc/_build/html/_static/pyescpos.ico
doc/_build/latex/Makefile
doc/_static/.gitignore
doc/api/config.rst
doc/api/constants.rst
doc/api/escpos.rst
doc/api/exceptions.rst
doc/api/image.rst
doc/api/printer.rst
doc/dev/changelog.rst
doc/dev/contributing.rst
doc/download/barcode.bin
doc/user/barcode.rst
doc/user/installation.rst
doc/user/methods.rst
doc/user/printers.rst
doc/user/raspi.rst
doc/user/todo.rst
doc/user/usage.rst
src/__init__.py
src/escpos/__init__.py
src/escpos/cli.py
src/escpos/config.py
src/escpos/constants.py
src/escpos/escpos.py
src/escpos/exceptions.py
src/escpos/image.py
src/escpos/printer.py
src/escpos/version.py
src/python_escpos_win.egg-info/PKG-INFO
src/python_escpos_win.egg-info/SOURCES.txt
src/python_escpos_win.egg-info/dependency_links.txt
src/python_escpos_win.egg-info/entry_points.txt
src/python_escpos_win.egg-info/requires.txt
src/python_escpos_win.egg-info/top_level.txt
test/Dies ist ein Test.LF.txt
test/test_abstract_base_class.py
test/test_cli.py
test/test_function_image.py
test/test_function_panel_button.py
test/test_function_qr_native.py
test/test_function_qr_non-native.py
