Metadata-Version: 2.1
Name: python-escpos-win
Version: 1.0.1
Summary: Python library to manipulate ESC/POS Printers
Home-page: https://github.com/python-escpos/python-escpos
Author: Manuel F Martinez and others
Author-email: manpaz@bashlinux.com
Maintainer: Patrick Kanzler
Maintainer-email: info@isaackogan.com
License: GNU GPL v3
Download-URL: https://github.com/isaac/python-escpos-win/archive/master.zip
Keywords: ESC/POS,thermoprinter,voucher printer,printing,receipt,
Platform: any
Classifier: Development Status :: 4 - Beta
Classifier: Environment :: Console
Classifier: Intended Audience :: Developers
Classifier: License :: OSI Approved :: GNU General Public License v3 (GPLv3)
Classifier: Operating System :: OS Independent
Classifier: Programming Language :: Python
Classifier: Programming Language :: Python :: 2
Classifier: Programming Language :: Python :: 2.7
Classifier: Programming Language :: Python :: 3
Classifier: Programming Language :: Python :: 3.3
Classifier: Programming Language :: Python :: 3.4
Classifier: Programming Language :: Python :: 3.5
Classifier: Programming Language :: Python :: Implementation :: CPython
Classifier: Programming Language :: Python :: Implementation :: PyPy
Classifier: Topic :: Software Development :: Libraries :: Python Modules
Classifier: Topic :: Office/Business :: Financial :: Point-Of-Sale
License-File: COPYING
